{
  "cordova": {
    "platforms": [
      "ios",
      "browser",
      "android"
    ],
    "plugins": {
      "com-darryncampbell-cordova-plugin-intent": {},
      "cordova-clipboard": {},
      "cordova-plugin-badge": {},
      "cordova-plugin-camera": {
        "ANDROID_SUPPORT_V4_VERSION": "27.+"
      },
      "cordova-plugin-customurlscheme": {
        "URL_SCHEME": "moodlemobile",
        "ANDROID_SCHEME": " ",
        "ANDROID_HOST": " ",
        "ANDROID_PATHPREFIX": "/"
      },
      "cordova-plugin-device": {},
      "cordova-plugin-file": {},
      "cordova-plugin-file-opener2": {
        "ANDROID_SUPPORT_V4_VERSION": "27.+"
      },
      "cordova-plugin-file-transfer": {},
      "cordova-plugin-globalization": {},
      "cordova-plugin-inappbrowser": {},
      "cordova-plugin-ionic-keyboard": {},
      "cordova-plugin-local-notification": {
        "ANDROID_SUPPORT_V4_VERSION": "26.+"
      },
      "cordova-plugin-media-capture": {},
      "cordova-plugin-network-information": {},
      "cordova-plugin-screen-orientation": {},
      "cordova-plugin-splashscreen": {},
      "cordova-plugin-statusbar": {},
      "cordova-plugin-whitelist": {},
      "cordova-plugin-zip": {},
      "cordova-sqlite-storage": {},
      "nl.kingsquare.cordova.background-audio": {},
      "phonegap-plugin-push": {
        "ANDROID_SUPPORT_V13_VERSION": "27.+",
        "FCM_VERSION": "17.5.+"
      },
      "cordova-plugin-ionic-webview": {
        "ANDROID_SUPPORT_ANNOTATIONS_VERSION": "27.+"
      },
      "cordova-plugin-advanced-http": {
        "OKHTTP_VERSION": "3.10.0"
      },
      "cordova-plugin-wkwebview-cookies": {},
      "cordova-plugin-qrscanner": {},
      "cordova-plugin-chooser": {},
      "cordova-plugin-wkuserscript": {},
      "cordova-plugin-geolocation": {
        "GPS_REQUIRED": "false"
      },
      "cordova-android-support-gradle-release": {
        "ANDROID_SUPPORT_VERSION": "27.0.0"
      }
    }
  },
  "dependencies": {
    "android": "0.0.8",
    "cordova-android": "^8.1.0",
    "cordova-support-google-services": "^1.2.1",
    "es6-promise-plugin": "^4.2.2",
    "phonegap-plugin-multidex": "^1.0.0",
    "xcode": "^3.0.1"
  }
}